README.rst
setup.py
btlejack/__init__.py
btlejack/helpers.py
btlejack/interface.py
btlejack/jobs.py
btlejack/link.py
btlejack/packets.py
btlejack/pcap.py
btlejack/session.py
btlejack/supervisors.py
btlejack/ui.py
btlejack/version.py
btlejack.egg-info/PKG-INFO
btlejack.egg-info/SOURCES.txt
btlejack.egg-info/dependency_links.txt
btlejack.egg-info/entry_points.txt
btlejack.egg-info/requires.txt
btlejack.egg-info/top_level.txt
btlejack/data/btlejack-fw-v1.hex
btlejack/data/btlejack-fw-v2.hex
btlejack/dissect/__init__.py
btlejack/dissect/att.py
btlejack/dissect/l2cap.py