Metadata-Version: 1.2
Name: btlejack
Version: 2.1.1
Summary: Bluetooth Low Energy Swiss-army knife to sniff, jam and hijack connections
Home-page: https://github.com/virtualabs/btlejack
Author: Damien Cauquil
Author-email: damien.cauquil@digital.security
License: MIT
Keywords: bluetooth smart low energy hijack sniff jam
Platform: UNKNOWN
Requires-Python: >3.5.2
